{"format":"vimfu-frames","version":1,"title":"VimFu \u2014 Why Not Arrow Keys?","source":"C:\\source\\vimfu\\curriculum\\shorts\\0014_why_not_arrow_keys.json","rows":20,"cols":40,"defaultFg":"d4d4d4","defaultBg":"000000","frameCount":13,"frames":[{"rows":20,"cols":40,"cursor":{"row":0,"col":9,"visible":true},"defaultFg":"d4d4d4","defaultBg":"000000","lines":[{"text":"\u279c  vimfu                                ","runs":[{"n":3,"fg":"00ff00","bg":"000000","b":true},{"n":5,"fg":"00ffff","bg":"000000","b":true},{"n":32,"fg":"d4d4d4","bg":"000000"}]},{"text":"                                        ","runs":[{"n":40,"fg":"d4d4d4","bg":"000000"}]},{"text":"                                        ","runs":[{"n":40,"fg":"d4d4d4","bg":"000000"}]},{"text":"                                        ","runs":[{"n":40,"fg":"d4d4d4","bg":"000000"}]},{"text":"                                        ","runs":[{"n":40,"fg":"d4d4d4","bg":"000000"}]},{"text":"                                        ","runs":[{"n":40,"fg":"d4d4d4","bg":"000000"}]},{"text":"                                        ","runs":[{"n":40,"fg":"d4d4d4","bg":"000000"}]},{"text":"                                        ","runs":[{"n":40,"fg":"d4d4d4","bg":"000000"}]},{"text":"                                        ","runs":[{"n":40,"fg":"d4d4d4","bg":"000000"}]},{"text":"                                        ","runs":[{"n":40,"fg":"d4d4d4","bg":"000000"}]},{"text":"                                        ","runs":[{"n":40,"fg":"d4d4d4","bg":"000000"}]},{"text":"                                        ","runs":[{"n":40,"fg":"d4d4d4","bg":"000000"}]},{"text":"                                        ","runs":[{"n":40,"fg":"d4d4d4","bg":"000000"}]},{"text":"                                        ","runs":[{"n":40,"fg":"d4d4d4","bg":"000000"}]},{"text":"                                        ","runs":[{"n":40,"fg":"d4d4d4","bg":"000000"}]},{"text":"                                        ","runs":[{"n":40,"fg":"d4d4d4","bg":"000000"}]},{"text":"                                        ","runs":[{"n":40,"fg":"d4d4d4","bg":"000000"}]},{"text":"                                        ","runs":[{"n":40,"fg":"d4d4d4","bg":"000000"}]},{"text":"                                        ","runs":[{"n":40,"fg":"d4d4d4","bg":"000000"}]},{"text":"                                        ","runs":[{"n":40,"fg":"d4d4d4","bg":"000000"}]}],"ms":0,"action":{"type":"start"}},{"rows":20,"cols":40,"cursor":{"row":1,"col":0,"visible":true},"defaultFg":"d4d4d4","defaultBg":"000000","lines":[{"text":"\u279c  vimfu nvim moves.py                  ","runs":[{"n":3,"fg":"00ff00","bg":"000000","b":true},{"n":5,"fg":"00ffff","bg":"000000","b":true},{"n":32,"fg":"d4d4d4","bg":"000000"}]},{"text":"                                        ","runs":[{"n":40,"fg":"d4d4d4","bg":"000000"}]},{"text":"                                        ","runs":[{"n":40,"fg":"d4d4d4","bg":"000000"}]},{"text":"                                        ","runs":[{"n":40,"fg":"d4d4d4","bg":"000000"}]},{"text":"                                        ","runs":[{"n":40,"fg":"d4d4d4","bg":"000000"}]},{"text":"                                        ","runs":[{"n":40,"fg":"d4d4d4","bg":"000000"}]},{"text":"                                        ","runs":[{"n":40,"fg":"d4d4d4","bg":"000000"}]},{"text":"                                        ","runs":[{"n":40,"fg":"d4d4d4","bg":"000000"}]},{"text":"                                        ","runs":[{"n":40,"fg":"d4d4d4","bg":"000000"}]},{"text":"                                        ","runs":[{"n":40,"fg":"d4d4d4","bg":"000000"}]},{"text":"                                        ","runs":[{"n":40,"fg":"d4d4d4","bg":"000000"}]},{"text":"                                        ","runs":[{"n":40,"fg":"d4d4d4","bg":"000000"}]},{"text":"                                        ","runs":[{"n":40,"fg":"d4d4d4","bg":"000000"}]},{"text":"                                        ","runs":[{"n":40,"fg":"d4d4d4","bg":"000000"}]},{"text":"                                        ","runs":[{"n":40,"fg":"d4d4d4","bg":"000000"}]},{"text":"                                        ","runs":[{"n":40,"fg":"d4d4d4","bg":"000000"}]},{"text":"                                        ","runs":[{"n":40,"fg":"d4d4d4","bg":"000000"}]},{"text":"                                        ","runs":[{"n":40,"fg":"d4d4d4","bg":"000000"}]},{"text":"                                        ","runs":[{"n":40,"fg":"d4d4d4","bg":"000000"}]},{"text":"                                        ","runs":[{"n":40,"fg":"d4d4d4","bg":"000000"}]}],"ms":2680,"action":{"type":"line","detail":"nvim moves.py","say":"Arrow keys work in Vim. Let's prove it.","overlay":"VimFu","overlayCaption":"Why Not Arrow Keys?"}},{"rows":20,"cols":40,"cursor":{"row":0,"col":0,"visible":true},"defaultFg":"d4d4d4","defaultBg":"000000","lines":[{"text":"apples = 10                             ","runs":[{"n":9,"fg":"d4d4d4","bg":"000000"},{"n":2,"fg":"ae81ff","bg":"000000"},{"n":29,"fg":"d4d4d4","bg":"000000"}]},{"text":"bananas = 20                            ","runs":[{"n":10,"fg":"d4d4d4","bg":"000000"},{"n":2,"fg":"ae81ff","bg":"000000"},{"n":28,"fg":"d4d4d4","bg":"000000"}]},{"text":"cherries = 30                           ","runs":[{"n":11,"fg":"d4d4d4","bg":"000000"},{"n":2,"fg":"ae81ff","bg":"000000"},{"n":27,"fg":"d4d4d4","bg":"000000"}]},{"text":"dates = 40                              ","runs":[{"n":8,"fg":"d4d4d4","bg":"000000"},{"n":2,"fg":"ae81ff","bg":"000000"},{"n":30,"fg":"d4d4d4","bg":"000000"}]},{"text":"~                                       ","runs":[{"n":40,"fg":"000000","bg":"000000"}]},{"text":"~                                       ","runs":[{"n":40,"fg":"000000","bg":"000000"}]},{"text":"~                                       ","runs":[{"n":40,"fg":"000000","bg":"000000"}]},{"text":"~                                       ","runs":[{"n":40,"fg":"000000","bg":"000000"}]},{"text":"~                                       ","runs":[{"n":40,"fg":"000000","bg":"000000"}]},{"text":"~                                       ","runs":[{"n":40,"fg":"000000","bg":"000000"}]},{"text":"~                                       ","runs":[{"n":40,"fg":"000000","bg":"000000"}]},{"text":"~                                       ","runs":[{"n":40,"fg":"000000","bg":"000000"}]},{"text":"~                                       ","runs":[{"n":40,"fg":"000000","bg":"000000"}]},{"text":"~                                       ","runs":[{"n":40,"fg":"000000","bg":"000000"}]},{"text":"~                                       ","runs":[{"n":40,"fg":"000000","bg":"000000"}]},{"text":"~                                       ","runs":[{"n":40,"fg":"000000","bg":"000000"}]},{"text":"~                                       ","runs":[{"n":40,"fg":"000000","bg":"000000"}]},{"text":"~                                       ","runs":[{"n":40,"fg":"000000","bg":"000000"}]},{"text":"moves.py              1,1            All","runs":[{"n":40,"fg":"b1b1b1","bg":"2e323c"}]},{"text":"                                        ","runs":[{"n":40,"fg":"d4d4d4","bg":"000000"}]}],"ms":6832,"action":{"type":"ifScreen","detail":"swap file"}},{"rows":20,"cols":40,"cursor":{"row":1,"col":0,"visible":true},"defaultFg":"d4d4d4","defaultBg":"000000","lines":[{"text":"apples = 10                             ","runs":[{"n":9,"fg":"d4d4d4","bg":"000000"},{"n":2,"fg":"ae81ff","bg":"000000"},{"n":29,"fg":"d4d4d4","bg":"000000"}]},{"text":"bananas = 20                            ","runs":[{"n":10,"fg":"d4d4d4","bg":"000000"},{"n":2,"fg":"ae81ff","bg":"000000"},{"n":28,"fg":"d4d4d4","bg":"000000"}]},{"text":"cherries = 30                           ","runs":[{"n":11,"fg":"d4d4d4","bg":"000000"},{"n":2,"fg":"ae81ff","bg":"000000"},{"n":27,"fg":"d4d4d4","bg":"000000"}]},{"text":"dates = 40                              ","runs":[{"n":8,"fg":"d4d4d4","bg":"000000"},{"n":2,"fg":"ae81ff","bg":"000000"},{"n":30,"fg":"d4d4d4","bg":"000000"}]},{"text":"~                                       ","runs":[{"n":40,"fg":"000000","bg":"000000"}]},{"text":"~                                       ","runs":[{"n":40,"fg":"000000","bg":"000000"}]},{"text":"~                                       ","runs":[{"n":40,"fg":"000000","bg":"000000"}]},{"text":"~                                       ","runs":[{"n":40,"fg":"000000","bg":"000000"}]},{"text":"~                                       ","runs":[{"n":40,"fg":"000000","bg":"000000"}]},{"text":"~                                       ","runs":[{"n":40,"fg":"000000","bg":"000000"}]},{"text":"~                                       ","runs":[{"n":40,"fg":"000000","bg":"000000"}]},{"text":"~                                       ","runs":[{"n":40,"fg":"000000","bg":"000000"}]},{"text":"~                                       ","runs":[{"n":40,"fg":"000000","bg":"000000"}]},{"text":"~                                       ","runs":[{"n":40,"fg":"000000","bg":"000000"}]},{"text":"~                                       ","runs":[{"n":40,"fg":"000000","bg":"000000"}]},{"text":"~                                       ","runs":[{"n":40,"fg":"000000","bg":"000000"}]},{"text":"~                                       ","runs":[{"n":40,"fg":"000000","bg":"000000"}]},{"text":"~                                       ","runs":[{"n":40,"fg":"000000","bg":"000000"}]},{"text":"moves.py              2,1            All","runs":[{"n":40,"fg":"b1b1b1","bg":"2e323c"}]},{"text":"                                        ","runs":[{"n":40,"fg":"d4d4d4","bg":"000000"}]}],"ms":8839,"action":{"type":"keys","detail":"\u001b[B","say":"Down, down, right, right, up.","keyOverlay":"\u001b[B"}},{"rows":20,"cols":40,"cursor":{"row":2,"col":0,"visible":true},"defaultFg":"d4d4d4","defaultBg":"000000","lines":[{"text":"apples = 10                             ","runs":[{"n":9,"fg":"d4d4d4","bg":"000000"},{"n":2,"fg":"ae81ff","bg":"000000"},{"n":29,"fg":"d4d4d4","bg":"000000"}]},{"text":"bananas = 20                            ","runs":[{"n":10,"fg":"d4d4d4","bg":"000000"},{"n":2,"fg":"ae81ff","bg":"000000"},{"n":28,"fg":"d4d4d4","bg":"000000"}]},{"text":"cherries = 30                           ","runs":[{"n":11,"fg":"d4d4d4","bg":"000000"},{"n":2,"fg":"ae81ff","bg":"000000"},{"n":27,"fg":"d4d4d4","bg":"000000"}]},{"text":"dates = 40                              ","runs":[{"n":8,"fg":"d4d4d4","bg":"000000"},{"n":2,"fg":"ae81ff","bg":"000000"},{"n":30,"fg":"d4d4d4","bg":"000000"}]},{"text":"~                                       ","runs":[{"n":40,"fg":"000000","bg":"000000"}]},{"text":"~                                       ","runs":[{"n":40,"fg":"000000","bg":"000000"}]},{"text":"~                                       ","runs":[{"n":40,"fg":"000000","bg":"000000"}]},{"text":"~                                       ","runs":[{"n":40,"fg":"000000","bg":"000000"}]},{"text":"~                                       ","runs":[{"n":40,"fg":"000000","bg":"000000"}]},{"text":"~                                       ","runs":[{"n":40,"fg":"000000","bg":"000000"}]},{"text":"~                                       ","runs":[{"n":40,"fg":"000000","bg":"000000"}]},{"text":"~                                       ","runs":[{"n":40,"fg":"000000","bg":"000000"}]},{"text":"~                                       ","runs":[{"n":40,"fg":"000000","bg":"000000"}]},{"text":"~                                       ","runs":[{"n":40,"fg":"000000","bg":"000000"}]},{"text":"~                                       ","runs":[{"n":40,"fg":"000000","bg":"000000"}]},{"text":"~                                       ","runs":[{"n":40,"fg":"000000","bg":"000000"}]},{"text":"~                                       ","runs":[{"n":40,"fg":"000000","bg":"000000"}]},{"text":"~                                       ","runs":[{"n":40,"fg":"000000","bg":"000000"}]},{"text":"moves.py              3,1            All","runs":[{"n":40,"fg":"b1b1b1","bg":"2e323c"}]},{"text":"                                        ","runs":[{"n":40,"fg":"d4d4d4","bg":"000000"}]}],"ms":9935,"action":{"type":"keys","detail":"\u001b[B","keyOverlay":"\u001b[B"}},{"rows":20,"cols":40,"cursor":{"row":2,"col":1,"visible":true},"defaultFg":"d4d4d4","defaultBg":"000000","lines":[{"text":"apples = 10                             ","runs":[{"n":9,"fg":"d4d4d4","bg":"000000"},{"n":2,"fg":"ae81ff","bg":"000000"},{"n":29,"fg":"d4d4d4","bg":"000000"}]},{"text":"bananas = 20                            ","runs":[{"n":10,"fg":"d4d4d4","bg":"000000"},{"n":2,"fg":"ae81ff","bg":"000000"},{"n":28,"fg":"d4d4d4","bg":"000000"}]},{"text":"cherries = 30                           ","runs":[{"n":11,"fg":"d4d4d4","bg":"000000"},{"n":2,"fg":"ae81ff","bg":"000000"},{"n":27,"fg":"d4d4d4","bg":"000000"}]},{"text":"dates = 40                              ","runs":[{"n":8,"fg":"d4d4d4","bg":"000000"},{"n":2,"fg":"ae81ff","bg":"000000"},{"n":30,"fg":"d4d4d4","bg":"000000"}]},{"text":"~                                       ","runs":[{"n":40,"fg":"000000","bg":"000000"}]},{"text":"~                                       ","runs":[{"n":40,"fg":"000000","bg":"000000"}]},{"text":"~                                       ","runs":[{"n":40,"fg":"000000","bg":"000000"}]},{"text":"~                                       ","runs":[{"n":40,"fg":"000000","bg":"000000"}]},{"text":"~                                       ","runs":[{"n":40,"fg":"000000","bg":"000000"}]},{"text":"~                                       ","runs":[{"n":40,"fg":"000000","bg":"000000"}]},{"text":"~                                       ","runs":[{"n":40,"fg":"000000","bg":"000000"}]},{"text":"~                                       ","runs":[{"n":40,"fg":"000000","bg":"000000"}]},{"text":"~                                       ","runs":[{"n":40,"fg":"000000","bg":"000000"}]},{"text":"~                                       ","runs":[{"n":40,"fg":"000000","bg":"000000"}]},{"text":"~                                       ","runs":[{"n":40,"fg":"000000","bg":"000000"}]},{"text":"~                                       ","runs":[{"n":40,"fg":"000000","bg":"000000"}]},{"text":"~                                       ","runs":[{"n":40,"fg":"000000","bg":"000000"}]},{"text":"~                                       ","runs":[{"n":40,"fg":"000000","bg":"000000"}]},{"text":"moves.py              3,2            All","runs":[{"n":40,"fg":"b1b1b1","bg":"2e323c"}]},{"text":"                                        ","runs":[{"n":40,"fg":"d4d4d4","bg":"000000"}]}],"ms":11029,"action":{"type":"keys","detail":"\u001b[C","keyOverlay":"\u001b[C"}},{"rows":20,"cols":40,"cursor":{"row":2,"col":2,"visible":true},"defaultFg":"d4d4d4","defaultBg":"000000","lines":[{"text":"apples = 10                             ","runs":[{"n":9,"fg":"d4d4d4","bg":"000000"},{"n":2,"fg":"ae81ff","bg":"000000"},{"n":29,"fg":"d4d4d4","bg":"000000"}]},{"text":"bananas = 20                            ","runs":[{"n":10,"fg":"d4d4d4","bg":"000000"},{"n":2,"fg":"ae81ff","bg":"000000"},{"n":28,"fg":"d4d4d4","bg":"000000"}]},{"text":"cherries = 30                           ","runs":[{"n":11,"fg":"d4d4d4","bg":"000000"},{"n":2,"fg":"ae81ff","bg":"000000"},{"n":27,"fg":"d4d4d4","bg":"000000"}]},{"text":"dates = 40                              ","runs":[{"n":8,"fg":"d4d4d4","bg":"000000"},{"n":2,"fg":"ae81ff","bg":"000000"},{"n":30,"fg":"d4d4d4","bg":"000000"}]},{"text":"~                                       ","runs":[{"n":40,"fg":"000000","bg":"000000"}]},{"text":"~                                       ","runs":[{"n":40,"fg":"000000","bg":"000000"}]},{"text":"~                                       ","runs":[{"n":40,"fg":"000000","bg":"000000"}]},{"text":"~                                       ","runs":[{"n":40,"fg":"000000","bg":"000000"}]},{"text":"~                                       ","runs":[{"n":40,"fg":"000000","bg":"000000"}]},{"text":"~                                       ","runs":[{"n":40,"fg":"000000","bg":"000000"}]},{"text":"~                                       ","runs":[{"n":40,"fg":"000000","bg":"000000"}]},{"text":"~                                       ","runs":[{"n":40,"fg":"000000","bg":"000000"}]},{"text":"~                                       ","runs":[{"n":40,"fg":"000000","bg":"000000"}]},{"text":"~                                       ","runs":[{"n":40,"fg":"000000","bg":"000000"}]},{"text":"~                                       ","runs":[{"n":40,"fg":"000000","bg":"000000"}]},{"text":"~                                       ","runs":[{"n":40,"fg":"000000","bg":"000000"}]},{"text":"~                                       ","runs":[{"n":40,"fg":"000000","bg":"000000"}]},{"text":"~                                       ","runs":[{"n":40,"fg":"000000","bg":"000000"}]},{"text":"moves.py              3,3            All","runs":[{"n":40,"fg":"b1b1b1","bg":"2e323c"}]},{"text":"                                        ","runs":[{"n":40,"fg":"d4d4d4","bg":"000000"}]}],"ms":12124,"action":{"type":"keys","detail":"\u001b[C","keyOverlay":"\u001b[C"}},{"rows":20,"cols":40,"cursor":{"row":1,"col":2,"visible":true},"defaultFg":"d4d4d4","defaultBg":"000000","lines":[{"text":"apples = 10                             ","runs":[{"n":9,"fg":"d4d4d4","bg":"000000"},{"n":2,"fg":"ae81ff","bg":"000000"},{"n":29,"fg":"d4d4d4","bg":"000000"}]},{"text":"bananas = 20                            ","runs":[{"n":10,"fg":"d4d4d4","bg":"000000"},{"n":2,"fg":"ae81ff","bg":"000000"},{"n":28,"fg":"d4d4d4","bg":"000000"}]},{"text":"cherries = 30                           ","runs":[{"n":11,"fg":"d4d4d4","bg":"000000"},{"n":2,"fg":"ae81ff","bg":"000000"},{"n":27,"fg":"d4d4d4","bg":"000000"}]},{"text":"dates = 40                              ","runs":[{"n":8,"fg":"d4d4d4","bg":"000000"},{"n":2,"fg":"ae81ff","bg":"000000"},{"n":30,"fg":"d4d4d4","bg":"000000"}]},{"text":"~                                       ","runs":[{"n":40,"fg":"000000","bg":"000000"}]},{"text":"~                                       ","runs":[{"n":40,"fg":"000000","bg":"000000"}]},{"text":"~                                       ","runs":[{"n":40,"fg":"000000","bg":"000000"}]},{"text":"~                                       ","runs":[{"n":40,"fg":"000000","bg":"000000"}]},{"text":"~                                       ","runs":[{"n":40,"fg":"000000","bg":"000000"}]},{"text":"~                                       ","runs":[{"n":40,"fg":"000000","bg":"000000"}]},{"text":"~                                       ","runs":[{"n":40,"fg":"000000","bg":"000000"}]},{"text":"~                                       ","runs":[{"n":40,"fg":"000000","bg":"000000"}]},{"text":"~                                       ","runs":[{"n":40,"fg":"000000","bg":"000000"}]},{"text":"~                                       ","runs":[{"n":40,"fg":"000000","bg":"000000"}]},{"text":"~                                       ","runs":[{"n":40,"fg":"000000","bg":"000000"}]},{"text":"~                                       ","runs":[{"n":40,"fg":"000000","bg":"000000"}]},{"text":"~                                       ","runs":[{"n":40,"fg":"000000","bg":"000000"}]},{"text":"~                                       ","runs":[{"n":40,"fg":"000000","bg":"000000"}]},{"text":"moves.py              2,3            All","runs":[{"n":40,"fg":"b1b1b1","bg":"2e323c"}]},{"text":"                                        ","runs":[{"n":40,"fg":"d4d4d4","bg":"000000"}]}],"ms":13220,"action":{"type":"keys","detail":"\u001b[A","keyOverlay":"\u001b[A"}},{"rows":20,"cols":40,"cursor":{"row":2,"col":2,"visible":true},"defaultFg":"d4d4d4","defaultBg":"000000","lines":[{"text":"apples = 10                             ","runs":[{"n":9,"fg":"d4d4d4","bg":"000000"},{"n":2,"fg":"ae81ff","bg":"000000"},{"n":29,"fg":"d4d4d4","bg":"000000"}]},{"text":"bananas = 20                            ","runs":[{"n":10,"fg":"d4d4d4","bg":"000000"},{"n":2,"fg":"ae81ff","bg":"000000"},{"n":28,"fg":"d4d4d4","bg":"000000"}]},{"text":"cherries = 30                           ","runs":[{"n":11,"fg":"d4d4d4","bg":"000000"},{"n":2,"fg":"ae81ff","bg":"000000"},{"n":27,"fg":"d4d4d4","bg":"000000"}]},{"text":"dates = 40                              ","runs":[{"n":8,"fg":"d4d4d4","bg":"000000"},{"n":2,"fg":"ae81ff","bg":"000000"},{"n":30,"fg":"d4d4d4","bg":"000000"}]},{"text":"~                                       ","runs":[{"n":40,"fg":"000000","bg":"000000"}]},{"text":"~                                       ","runs":[{"n":40,"fg":"000000","bg":"000000"}]},{"text":"~                                       ","runs":[{"n":40,"fg":"000000","bg":"000000"}]},{"text":"~                                       ","runs":[{"n":40,"fg":"000000","bg":"000000"}]},{"text":"~                                       ","runs":[{"n":40,"fg":"000000","bg":"000000"}]},{"text":"~                                       ","runs":[{"n":40,"fg":"000000","bg":"000000"}]},{"text":"~                                       ","runs":[{"n":40,"fg":"000000","bg":"000000"}]},{"text":"~                                       ","runs":[{"n":40,"fg":"000000","bg":"000000"}]},{"text":"~                                       ","runs":[{"n":40,"fg":"000000","bg":"000000"}]},{"text":"~                                       ","runs":[{"n":40,"fg":"000000","bg":"000000"}]},{"text":"~                                       ","runs":[{"n":40,"fg":"000000","bg":"000000"}]},{"text":"~                                       ","runs":[{"n":40,"fg":"000000","bg":"000000"}]},{"text":"~                                       ","runs":[{"n":40,"fg":"000000","bg":"000000"}]},{"text":"~                                       ","runs":[{"n":40,"fg":"000000","bg":"000000"}]},{"text":"moves.py              3,3            All","runs":[{"n":40,"fg":"b1b1b1","bg":"2e323c"}]},{"text":"                                        ","runs":[{"n":40,"fg":"d4d4d4","bg":"000000"}]}],"ms":15225,"action":{"type":"keys","detail":"j","say":"With H J K L, your fingers never move.","keyOverlay":"j","keyCaption":"down"}},{"rows":20,"cols":40,"cursor":{"row":3,"col":2,"visible":true},"defaultFg":"d4d4d4","defaultBg":"000000","lines":[{"text":"apples = 10                             ","runs":[{"n":9,"fg":"d4d4d4","bg":"000000"},{"n":2,"fg":"ae81ff","bg":"000000"},{"n":29,"fg":"d4d4d4","bg":"000000"}]},{"text":"bananas = 20                            ","runs":[{"n":10,"fg":"d4d4d4","bg":"000000"},{"n":2,"fg":"ae81ff","bg":"000000"},{"n":28,"fg":"d4d4d4","bg":"000000"}]},{"text":"cherries = 30                           ","runs":[{"n":11,"fg":"d4d4d4","bg":"000000"},{"n":2,"fg":"ae81ff","bg":"000000"},{"n":27,"fg":"d4d4d4","bg":"000000"}]},{"text":"dates = 40                              ","runs":[{"n":8,"fg":"d4d4d4","bg":"000000"},{"n":2,"fg":"ae81ff","bg":"000000"},{"n":30,"fg":"d4d4d4","bg":"000000"}]},{"text":"~                                       ","runs":[{"n":40,"fg":"000000","bg":"000000"}]},{"text":"~                                       ","runs":[{"n":40,"fg":"000000","bg":"000000"}]},{"text":"~                                       ","runs":[{"n":40,"fg":"000000","bg":"000000"}]},{"text":"~                                       ","runs":[{"n":40,"fg":"000000","bg":"000000"}]},{"text":"~                                       ","runs":[{"n":40,"fg":"000000","bg":"000000"}]},{"text":"~                                       ","runs":[{"n":40,"fg":"000000","bg":"000000"}]},{"text":"~                                       ","runs":[{"n":40,"fg":"000000","bg":"000000"}]},{"text":"~                                       ","runs":[{"n":40,"fg":"000000","bg":"000000"}]},{"text":"~                                       ","runs":[{"n":40,"fg":"000000","bg":"000000"}]},{"text":"~                                       ","runs":[{"n":40,"fg":"000000","bg":"000000"}]},{"text":"~                                       ","runs":[{"n":40,"fg":"000000","bg":"000000"}]},{"text":"~                                       ","runs":[{"n":40,"fg":"000000","bg":"000000"}]},{"text":"~                                       ","runs":[{"n":40,"fg":"000000","bg":"000000"}]},{"text":"~                                       ","runs":[{"n":40,"fg":"000000","bg":"000000"}]},{"text":"moves.py              4,3            All","runs":[{"n":40,"fg":"b1b1b1","bg":"2e323c"}]},{"text":"                                        ","runs":[{"n":40,"fg":"d4d4d4","bg":"000000"}]}],"ms":16139,"action":{"type":"keys","detail":"j","keyOverlay":"j","keyCaption":"down"}},{"rows":20,"cols":40,"cursor":{"row":3,"col":3,"visible":true},"defaultFg":"d4d4d4","defaultBg":"000000","lines":[{"text":"apples = 10                             ","runs":[{"n":9,"fg":"d4d4d4","bg":"000000"},{"n":2,"fg":"ae81ff","bg":"000000"},{"n":29,"fg":"d4d4d4","bg":"000000"}]},{"text":"bananas = 20                            ","runs":[{"n":10,"fg":"d4d4d4","bg":"000000"},{"n":2,"fg":"ae81ff","bg":"000000"},{"n":28,"fg":"d4d4d4","bg":"000000"}]},{"text":"cherries = 30                           ","runs":[{"n":11,"fg":"d4d4d4","bg":"000000"},{"n":2,"fg":"ae81ff","bg":"000000"},{"n":27,"fg":"d4d4d4","bg":"000000"}]},{"text":"dates = 40                              ","runs":[{"n":8,"fg":"d4d4d4","bg":"000000"},{"n":2,"fg":"ae81ff","bg":"000000"},{"n":30,"fg":"d4d4d4","bg":"000000"}]},{"text":"~                                       ","runs":[{"n":40,"fg":"000000","bg":"000000"}]},{"text":"~                                       ","runs":[{"n":40,"fg":"000000","bg":"000000"}]},{"text":"~                                       ","runs":[{"n":40,"fg":"000000","bg":"000000"}]},{"text":"~                                       ","runs":[{"n":40,"fg":"000000","bg":"000000"}]},{"text":"~                                       ","runs":[{"n":40,"fg":"000000","bg":"000000"}]},{"text":"~                                       ","runs":[{"n":40,"fg":"000000","bg":"000000"}]},{"text":"~                                       ","runs":[{"n":40,"fg":"000000","bg":"000000"}]},{"text":"~                                       ","runs":[{"n":40,"fg":"000000","bg":"000000"}]},{"text":"~                                       ","runs":[{"n":40,"fg":"000000","bg":"000000"}]},{"text":"~                                       ","runs":[{"n":40,"fg":"000000","bg":"000000"}]},{"text":"~                                       ","runs":[{"n":40,"fg":"000000","bg":"000000"}]},{"text":"~                                       ","runs":[{"n":40,"fg":"000000","bg":"000000"}]},{"text":"~                                       ","runs":[{"n":40,"fg":"000000","bg":"000000"}]},{"text":"~                                       ","runs":[{"n":40,"fg":"000000","bg":"000000"}]},{"text":"moves.py              4,4            All","runs":[{"n":40,"fg":"b1b1b1","bg":"2e323c"}]},{"text":"                                        ","runs":[{"n":40,"fg":"d4d4d4","bg":"000000"}]}],"ms":17051,"action":{"type":"keys","detail":"l","keyOverlay":"l","keyCaption":"right"}},{"rows":20,"cols":40,"cursor":{"row":3,"col":4,"visible":true},"defaultFg":"d4d4d4","defaultBg":"000000","lines":[{"text":"apples = 10                             ","runs":[{"n":9,"fg":"d4d4d4","bg":"000000"},{"n":2,"fg":"ae81ff","bg":"000000"},{"n":29,"fg":"d4d4d4","bg":"000000"}]},{"text":"bananas = 20                            ","runs":[{"n":10,"fg":"d4d4d4","bg":"000000"},{"n":2,"fg":"ae81ff","bg":"000000"},{"n":28,"fg":"d4d4d4","bg":"000000"}]},{"text":"cherries = 30                           ","runs":[{"n":11,"fg":"d4d4d4","bg":"000000"},{"n":2,"fg":"ae81ff","bg":"000000"},{"n":27,"fg":"d4d4d4","bg":"000000"}]},{"text":"dates = 40                              ","runs":[{"n":8,"fg":"d4d4d4","bg":"000000"},{"n":2,"fg":"ae81ff","bg":"000000"},{"n":30,"fg":"d4d4d4","bg":"000000"}]},{"text":"~                                       ","runs":[{"n":40,"fg":"000000","bg":"000000"}]},{"text":"~                                       ","runs":[{"n":40,"fg":"000000","bg":"000000"}]},{"text":"~                                       ","runs":[{"n":40,"fg":"000000","bg":"000000"}]},{"text":"~                                       ","runs":[{"n":40,"fg":"000000","bg":"000000"}]},{"text":"~                                       ","runs":[{"n":40,"fg":"000000","bg":"000000"}]},{"text":"~                                       ","runs":[{"n":40,"fg":"000000","bg":"000000"}]},{"text":"~                                       ","runs":[{"n":40,"fg":"000000","bg":"000000"}]},{"text":"~                                       ","runs":[{"n":40,"fg":"000000","bg":"000000"}]},{"text":"~                                       ","runs":[{"n":40,"fg":"000000","bg":"000000"}]},{"text":"~                                       ","runs":[{"n":40,"fg":"000000","bg":"000000"}]},{"text":"~                                       ","runs":[{"n":40,"fg":"000000","bg":"000000"}]},{"text":"~                                       ","runs":[{"n":40,"fg":"000000","bg":"000000"}]},{"text":"~                                       ","runs":[{"n":40,"fg":"000000","bg":"000000"}]},{"text":"~                                       ","runs":[{"n":40,"fg":"000000","bg":"000000"}]},{"text":"moves.py              4,5            All","runs":[{"n":40,"fg":"b1b1b1","bg":"2e323c"}]},{"text":"                                        ","runs":[{"n":40,"fg":"d4d4d4","bg":"000000"}]}],"ms":17964,"action":{"type":"keys","detail":"l","keyOverlay":"l","keyCaption":"right"}},{"rows":20,"cols":40,"cursor":{"row":2,"col":4,"visible":true},"defaultFg":"d4d4d4","defaultBg":"000000","lines":[{"text":"apples = 10                             ","runs":[{"n":9,"fg":"d4d4d4","bg":"000000"},{"n":2,"fg":"ae81ff","bg":"000000"},{"n":29,"fg":"d4d4d4","bg":"000000"}]},{"text":"bananas = 20                            ","runs":[{"n":10,"fg":"d4d4d4","bg":"000000"},{"n":2,"fg":"ae81ff","bg":"000000"},{"n":28,"fg":"d4d4d4","bg":"000000"}]},{"text":"cherries = 30                           ","runs":[{"n":11,"fg":"d4d4d4","bg":"000000"},{"n":2,"fg":"ae81ff","bg":"000000"},{"n":27,"fg":"d4d4d4","bg":"000000"}]},{"text":"dates = 40                              ","runs":[{"n":8,"fg":"d4d4d4","bg":"000000"},{"n":2,"fg":"ae81ff","bg":"000000"},{"n":30,"fg":"d4d4d4","bg":"000000"}]},{"text":"~                                       ","runs":[{"n":40,"fg":"000000","bg":"000000"}]},{"text":"~                                       ","runs":[{"n":40,"fg":"000000","bg":"000000"}]},{"text":"~                                       ","runs":[{"n":40,"fg":"000000","bg":"000000"}]},{"text":"~                                       ","runs":[{"n":40,"fg":"000000","bg":"000000"}]},{"text":"~                                       ","runs":[{"n":40,"fg":"000000","bg":"000000"}]},{"text":"~                                       ","runs":[{"n":40,"fg":"000000","bg":"000000"}]},{"text":"~                                       ","runs":[{"n":40,"fg":"000000","bg":"000000"}]},{"text":"~                                       ","runs":[{"n":40,"fg":"000000","bg":"000000"}]},{"text":"~                                       ","runs":[{"n":40,"fg":"000000","bg":"000000"}]},{"text":"~                                       ","runs":[{"n":40,"fg":"000000","bg":"000000"}]},{"text":"~                                       ","runs":[{"n":40,"fg":"000000","bg":"000000"}]},{"text":"~                                       ","runs":[{"n":40,"fg":"000000","bg":"000000"}]},{"text":"~                                       ","runs":[{"n":40,"fg":"000000","bg":"000000"}]},{"text":"~                                       ","runs":[{"n":40,"fg":"000000","bg":"000000"}]},{"text":"moves.py              3,5            All","runs":[{"n":40,"fg":"b1b1b1","bg":"2e323c"}]},{"text":"                                        ","runs":[{"n":40,"fg":"d4d4d4","bg":"000000"}]}],"ms":18877,"action":{"type":"keys","detail":"k","keyOverlay":"k","keyCaption":"up"}}]}