{
  "id": "survival.undo-redo",
  "title": "{key:u} and {key:Ctrl-R}",
  "summary": "Undo, then redo.",
  "topic": "survival.undo-redo",
  "frames": [
    {
      "n": 1,
      "color": "frame_01.color.svg",
      "bw": "frame_01.bw.svg",
      "caption": "",
      "narration": "",
      "keys": ""
    },
    {
      "n": 2,
      "color": "frame_02.color.svg",
      "bw": "frame_02.bw.svg",
      "caption": "{key:d}{key:d} deletes 'bravo'.",
      "narration": "",
      "keys": "dd"
    },
    {
      "n": 3,
      "color": "frame_03.color.svg",
      "bw": "frame_03.bw.svg",
      "caption": "{key:u} \u2014 bravo back.",
      "narration": "",
      "keys": "u"
    },
    {
      "n": 4,
      "color": "frame_04.color.svg",
      "bw": "frame_04.bw.svg",
      "caption": "{key:Ctrl-R} \u2014 redo (gone again).",
      "narration": "Undo and redo navigate the change history. Vim keeps a tree, not just a stack \u2014 see undo-tree.",
      "keys": "Ctrl-R"
    }
  ]
}