{
  "id": "dot.repeat",
  "title": ".",
  "summary": "The single most powerful key in Vim.",
  "topic": "dot.repeat",
  "frames": [
    {
      "n": 1,
      "color": "frame_01.color.svg",
      "bw": "frame_01.bw.svg",
      "caption": "",
      "narration": "",
      "keys": ""
    },
    {
      "n": 2,
      "color": "frame_02.color.svg",
      "bw": "frame_02.bw.svg",
      "caption": "{key:c}{key:w}, type `xxx`, {key:Esc}.",
      "narration": "",
      "keys": "cw Esc"
    },
    {
      "n": 3,
      "color": "frame_03.color.svg",
      "bw": "frame_03.bw.svg",
      "caption": ". \u2014 same change at new cursor.",
      "narration": "Dot replays the last *change* (anything that modified the buffer). Cheap revolution: structure your motions so dot becomes useful.",
      "keys": "j0 ."
    },
    {
      "n": 4,
      "color": "frame_04.color.svg",
      "bw": "frame_04.bw.svg",
      "caption": ". again \u2014 third line.",
      "narration": "Move-and-dot is a Vim idiom. Beats keyboard macros for trivial repetitions.",
      "keys": "j0 ."
    }
  ]
}